publications/__init__.py
publications/bibtex.py
publications/fields.py
publications/six.py
publications/urls.py
publications/utils.py
publications/admin/__init__.py
publications/admin/listadmin.py
publications/admin/orderedmodeladmin.py
publications/admin/publicationadmin.py
publications/admin/typeadmin.py
publications/admin_views/__init__.py
publications/admin_views/import_bibtex.py
publications/fixtures/initial_data.json
publications/fixtures/test_data.json
publications/migrations/0001_initial.py
publications/migrations/0002_initial_data.py
publications/migrations/__init__.py
publications/models/__init__.py
publications/models/customfile.py
publications/models/customlink.py
publications/models/list.py
publications/models/orderedmodel.py
publications/models/publication.py
publications/models/type.py
publications/static/ordered_model/arrow-down.gif
publications/static/ordered_model/arrow-up.gif
publications/templates/base.html
publications/templates/admin/publications/import_bibtex.html
publications/templates/admin/publications/order_controls.html
publications/templates/admin/publications/publication_change_list.html
publications/templates/publications/author.html
publications/templates/publications/id.html
publications/templates/publications/keyword.html
publications/templates/publications/list.html
publications/templates/publications/person.html
publications/templates/publications/publication.bib
publications/templates/publications/publication.html
publications/templates/publications/publications.bib
publications/templates/publications/publications.html
publications/templates/publications/publications.mods
publications/templates/publications/publications.ris
publications/templates/publications/publications.rss
publications/templates/publications/publications.txt
publications/templates/publications/publications_with_thumbnails.html
publications/templates/publications/years.html
publications/templatetags/__init__.py
publications/templatetags/publication_extras.py
django_publications-1.2.0.dist-info/LICENSE
django_publications-1.2.0.dist-info/METADATA
django_publications-1.2.0.dist-info/WHEEL
django_publications-1.2.0.dist-info/top_level.txt
django_publications-1.2.0.dist-info/RECORD
