Metadata-Version: 2.1
Name: django-publications
Version: 1.2.0
Summary: A Django app for managing scientific publications.
Home-page: https://github.com/lucastheis/django-publications
Author: Lucas Theis
Author-email: lucas@theis.io
License: MIT
Classifier: Development Status :: 3 - Alpha
Classifier: Environment :: Web Environment
Classifier: Framework :: Django
Classifier: Intended Audience :: Developers
Classifier: Intended Audience :: Science/Research
Classifier: License :: OSI Approved :: MIT License
Classifier: Operating System :: OS Independent
Classifier: Programming Language :: Python :: 3
Classifier: Programming Language :: Python :: 3.7
License-File: LICENSE
Requires-Dist: Django >=2.1.0
Requires-Dist: Pillow >=2.3.0
